MANIFEST.in
README.rst
setup.cfg
setup.py
betik_app_staff/__init__.py
betik_app_staff/admin.py
betik_app_staff/apps.py
betik_app_staff/enums.py
betik_app_staff/exceptions.py
betik_app_staff/filters.py
betik_app_staff/leave_calculator.py
betik_app_staff/managers.py
betik_app_staff/models.py
betik_app_staff/serializers_merge.py
betik_app_staff/serializers_statistic.py
betik_app_staff/tasks.py
betik_app_staff/urls.py
betik_app_staff/validators.py
betik_app_staff/working_day.py
betik_app_staff.egg-info/PKG-INFO
betik_app_staff.egg-info/SOURCES.txt
betik_app_staff.egg-info/dependency_links.txt
betik_app_staff.egg-info/top_level.txt
betik_app_staff/locale/tr/LC_MESSAGES/django.mo
betik_app_staff/locale/tr/LC_MESSAGES/django.po
betik_app_staff/management/commands/create_bank_holidays.py
betik_app_staff/management/commands/create_leave_types.py
betik_app_staff/management/commands/__pycache__/create_bank_holidays.cpython-38.pyc
betik_app_staff/management/commands/__pycache__/create_leave_types.cpython-38.pyc
betik_app_staff/migrations/0001_initial.py
betik_app_staff/migrations/0002_titlemodel.py
betik_app_staff/migrations/0003_stafftypemodel.py
betik_app_staff/migrations/0004_staffmodel.py
betik_app_staff/migrations/0005_auto_20210124_1955.py
betik_app_staff/migrations/0006_auto_20210124_2036.py
betik_app_staff/migrations/0007_passivereasonmodel.py
betik_app_staff/migrations/0008_passivestaffeventmodel.py
betik_app_staff/migrations/0009_auto_20210513_2210.py
betik_app_staff/migrations/0010_dismissreasonmodel.py
betik_app_staff/migrations/0011_dismissstafflogmodel.py
betik_app_staff/migrations/0012_auto_20210514_1506.py
betik_app_staff/migrations/0013_activereasonmodel.py
betik_app_staff/migrations/0014_activestafflogmodel.py
betik_app_staff/migrations/0015_bankholidaymodel.py
betik_app_staff/migrations/0016_auto_20211022_1123.py
betik_app_staff/migrations/0017_auto_20211022_1258.py
betik_app_staff/migrations/0018_auto_20211024_1836.py
betik_app_staff/migrations/0019_leavetypemodel.py
betik_app_staff/migrations/0020_auto_20211102_0938.py
betik_app_staff/migrations/0021_auto_20211116_1022.py
