Metadata-Version: 1.1
Name: betik-app-staff
Version: 1.5.0
Summary: This application provides opportunities such as recording all personal and registration information of employees in a corporate company, leave tracking, report, entry-exit times, overtime information.
Home-page: https://www.example.com/
Author: Erhan KOÃ‡LAR
Author-email: e.koclar@betik.com.tr
License: BSD-3-Clause  # Example license
Platform: UNKNOWN
Classifier: Environment :: Web Environment
Classifier: Framework :: Django
Classifier: Framework :: Django :: 3.0
Classifier: Intended Audience :: Developers
Classifier: License :: OSI Approved :: BSD License
Classifier: Operating System :: OS Independent
Classifier: Programming Language :: Python
Classifier: Programming Language :: Python :: 3
Classifier: Programming Language :: Python :: 3 :: Only
Classifier: Programming Language :: Python :: 3.6
Classifier: Programming Language :: Python :: 3.7
Classifier: Programming Language :: Python :: 3.8
Classifier: Topic :: Internet :: WWW/HTTP
Classifier: Topic :: Internet :: WWW/HTTP :: Dynamic Content
